<annotation>
	<folder>good prints</folder>
	<filename>11ea1501228410c018f07c14093a79cf_preview_featured.jpg</filename>
	<path>E:\Imon\3D printer\good prints\11ea1501228410c018f07c14093a79cf_preview_featured.jpg</path>
	<source>
		<database>Unknown</database>
	</source>
	<size>
		<width>628</width>
		<height>472</height>
		<depth>3</depth>
	</size>
	<segmented>0</segmented>
	<object>
		<name>Good</name>
		<pose>Unspecified</pose>
		<truncated>0</truncated>
		<difficult>0</difficult>
		<bndbox>
			<xmin>27</xmin>
			<ymin>33</ymin>
			<xmax>575</xmax>
			<ymax>391</ymax>
		</bndbox>
	</object>
</annotation>
